systemd_service/__init__.py
systemd_service-1.8.dist-info/LICENSE
systemd_service-1.8.dist-info/METADATA
systemd_service-1.8.dist-info/WHEEL
systemd_service-1.8.dist-info/top_level.txt
systemd_service-1.8.dist-info/RECORD
