Metadata-Version: 2.1
Name: systemd-service
Version: 1.8
Summary: Simple API to automate the creation of custom daemons for GNU/Linux.
Download-URL: https://github.com/UN-GCPDS/systemd-service
Author: Yeison Cardona
Author-email: yeisoneng@gmail.com
Maintainer: Yeison Cardona
Maintainer-email: yeisoneng@gmail.com
License: BSD-2-Clause
Platform: UNKNOWN
Classifier: License :: OSI Approved :: BSD License
Classifier: Programming Language :: Python :: 3.8
Classifier: Programming Language :: Python :: 3.9
Classifier: Programming Language :: Python :: 3.10
Requires-Python: >=3.7
License-File: LICENSE
